sentry_bearychat/__init__.py
sentry_bearychat/models.py
sentry_bearychat/plugin.py
sentry_bearychat-0.2.3.dist-info/DESCRIPTION.rst
sentry_bearychat-0.2.3.dist-info/entry_points.txt
sentry_bearychat-0.2.3.dist-info/METADATA
sentry_bearychat-0.2.3.dist-info/metadata.json
sentry_bearychat-0.2.3.dist-info/RECORD
sentry_bearychat-0.2.3.dist-info/top_level.txt
sentry_bearychat-0.2.3.dist-info/WHEEL
