Metadata-Version: 2.0
Name: sentry-bearychat
Version: 0.2.3
Summary: A Sentry extension which posts notifications to BearyChat (https://bearychat.com/).
Home-page: https://github.com/bearyinnovative/sentry-bearychat
Author: BearyInnovative
Author-email: info@bearyinnovative.com
License: BSD
Keywords: bearychat sentry
Platform: UNKNOWN
Classifier: Framework :: Django
Classifier: Intended Audience :: Developers
Classifier: Intended Audience :: System Administrators
Classifier: Operating System :: OS Independent
Classifier: Topic :: Software Development
Requires-Dist: sentry (>=5.0.0)
